CHANGES
LICENSE
MANIFEST.in
README.rst
setup.cfg
setup.py
tox.ini
zygomorphic/__init__.py
zygomorphic.egg-info/PKG-INFO
zygomorphic.egg-info/SOURCES.txt
zygomorphic.egg-info/dependency_links.txt
zygomorphic.egg-info/not-zip-safe
zygomorphic.egg-info/requires.txt
zygomorphic.egg-info/top_level.txt
zygomorphic/tests/__init__.py