Metadata-Version: 1.1
Name: zygomorphic
Version: 0.2.3
Summary: Zygomorphic!
Home-page: https://github.com/storborg/zygomorphic
Author: Scott Torborg
Author-email: storborg@gmail.com
License: MIT
Keywords: bumpr test
Platform: UNKNOWN
Classifier: Development Status :: 2 - Pre-Alpha
Classifier: License :: OSI Approved :: MIT License
Classifier: Programming Language :: Python :: 2
Classifier: Programming Language :: Python :: 2.7
Classifier: Topic :: Multimedia :: Graphics
